ansible_runner/__init__.py
ansible_runner/__main__.py
ansible_runner/cleanup.py
ansible_runner/defaults.py
ansible_runner/exceptions.py
ansible_runner/interface.py
ansible_runner/loader.py
ansible_runner/output.py
ansible_runner/runner.py
ansible_runner/runner_config.py
ansible_runner/streaming.py
ansible_runner/config/__init__.py
ansible_runner/config/_base.py
ansible_runner/config/ansible_cfg.py
ansible_runner/config/command.py
ansible_runner/config/doc.py
ansible_runner/config/inventory.py
ansible_runner/config/runner.py
ansible_runner/display_callback/__init__.py
ansible_runner/display_callback/callback/__init__.py
ansible_runner/display_callback/callback/awx_display.py
ansible_runner/plugins/__init__.py
ansible_runner/utils/__init__.py
ansible_runner/utils/base64io.py
ansible_runner/utils/capacity.py
ansible_runner/utils/importlib_compat.py
ansible_runner/utils/streaming.py
ansible_runner-2.4.0.dist-info/LICENSE.md
ansible_runner-2.4.0.dist-info/METADATA
ansible_runner-2.4.0.dist-info/WHEEL
ansible_runner-2.4.0.dist-info/entry_points.txt
ansible_runner-2.4.0.dist-info/top_level.txt
ansible_runner-2.4.0.dist-info/RECORD
