Metadata-Version: 2.1
Name: ansible-runner
Version: 2.4.0
Summary: "Consistent Ansible Python API and CLI with container and process isolation runtime capabilities"
Home-page: https://ansible-runner.readthedocs.io
Author: Ansible, Inc.
Author-email: info@ansible.com
License: Apache Software License, Version 2.0
Project-URL: Source, https://github.com/ansible/ansible-runner
Classifier: Development Status :: 5 - Production/Stable
Classifier: Environment :: Console
Classifier: Intended Audience :: Developers
Classifier: Intended Audience :: Information Technology
Classifier: Intended Audience :: System Administrators
Classifier: License :: OSI Approved :: Apache Software License
Classifier: Natural Language :: English
Classifier: Operating System :: POSIX
Classifier: Programming Language :: Python :: 3.9
Classifier: Programming Language :: Python :: 3.10
Classifier: Programming Language :: Python :: 3.11
Classifier: Programming Language :: Python :: 3.12
Classifier: Programming Language :: Python :: 3 :: Only
Classifier: Topic :: Software Development :: Libraries :: Python Modules
Classifier: Topic :: System :: Systems Administration
Classifier: Topic :: Utilities
Requires-Python: >=3.9
License-File: LICENSE.md
Requires-Dist: pexpect>=4.5
Requires-Dist: packaging
Requires-Dist: python-daemon
Requires-Dist: pyyaml
Requires-Dist: importlib-metadata<6.3,>=4.6; python_version < "3.10"
